kittycore/__init__.py
kittycore/cli.py
kittycore/kittycap.py
kittycap-1.1.7.dist-info/METADATA
kittycap-1.1.7.dist-info/WHEEL
kittycap-1.1.7.dist-info/entry_points.txt
kittycap-1.1.7.dist-info/top_level.txt
kittycap-1.1.7.dist-info/RECORD
