Metadata-Version: 2.1
Name: kittycap
Version: 1.1.7
Summary: KittyCap python interface
Home-page: https://github.com/kittycore/kittycap
Author: KittyCore
Author-email: code@kittycore.xyz
License: UNKNOWN
Platform: UNKNOWN
Classifier: Programming Language :: Python :: 3
Classifier: License :: OSI Approved :: MIT License
Classifier: Operating System :: OS Independent
Requires-Dist: requests
Requires-Dist: appdirs
Requires-Dist: argparse
